envparse-stubs/__init__.pyi
envparse_stubs-0.2.2.dist-info/LICENSE
envparse_stubs-0.2.2.dist-info/METADATA
envparse_stubs-0.2.2.dist-info/WHEEL
envparse_stubs-0.2.2.dist-info/top_level.txt
envparse_stubs-0.2.2.dist-info/RECORD
