Metadata-Version: 2.1
Name: envparse-stubs
Version: 0.2.2
Summary: Type stubs for the envparse library
Home-page: https://github.com/RJPercival/envparse-stubs
Author: Rob Percival
Author-email: rob.percival87@gmail.com
License: UNKNOWN
Platform: UNKNOWN
Classifier: Programming Language :: Python :: 3
Classifier: License :: OSI Approved :: MIT License
Classifier: Operating System :: OS Independent
Requires-Python: >=3.5
License-File: LICENSE
Requires-Dist: envparse (<1,>=0.2)
